nestcheck/__init__.py
nestcheck/_version.py
nestcheck/data_processing.py
nestcheck/diagnostics_tables.py
nestcheck/dummy_data.py
nestcheck/error_analysis.py
nestcheck/estimators.py
nestcheck/io_utils.py
nestcheck/ns_run_utils.py
nestcheck/pandas_functions.py
nestcheck/parallel_utils.py
nestcheck/plots.py
nestcheck/write_polychord_output.py
nestcheck-0.2.1.dist-info/LICENSE
nestcheck-0.2.1.dist-info/METADATA
nestcheck-0.2.1.dist-info/WHEEL
nestcheck-0.2.1.dist-info/top_level.txt
nestcheck-0.2.1.dist-info/RECORD
