Metadata-Version: 2.1
Name: nestcheck
Version: 0.2.1
Summary: Error analysis, diagnostic tests and plots for nested sampling calculations.
Home-page: https://github.com/ejhigson/nestcheck
Author: Edward Higson
Author-email: e.higson@mrao.cam.ac.uk
License: MIT
Project-URL: Docs, http://nestcheck.readthedocs.io/en/latest/
Keywords: nested-sampling sampling error-analysis
Platform: UNKNOWN
Classifier: Development Status :: 5 - Production/Stable
Classifier: Intended Audience :: Science/Research
Classifier: License :: OSI Approved :: MIT License
Classifier: Programming Language :: Python :: 2
Classifier: Programming Language :: Python :: 2.7
Classifier: Programming Language :: Python :: 3
Classifier: Programming Language :: Python :: 3.4
Classifier: Programming Language :: Python :: 3.5
Classifier: Programming Language :: Python :: 3.6
Classifier: Topic :: Scientific/Engineering :: Astronomy
Classifier: Topic :: Scientific/Engineering :: Physics
Classifier: Topic :: Scientific/Engineering :: Visualization
Classifier: Topic :: Scientific/Engineering :: Information Analysis
Provides-Extra: docs
